{
  "title": "Adani Group Stocks Surge 8% on New Infrastructure Contracts",
  "slug": "adani-group-stock-surge",
  "content": "<p>Adani Group companies witnessed sharp gains after securing major infrastructure contracts worth Rs 50,000 crore from state governments.</p>",
  "excerpt": "Adani stocks rally on major infrastructure deal announcements.",
  "author": "Fin24x Corporate Desk",
  "publishedDate": "2025-12-25",
  "premium": false,
  "views": 0,
  "tags": ["Adani Group", "Infrastructure", "Stock Rally", "Contracts"]
}

